image_processing/__init__.py
image_processing/processing/__init__.py
image_processing/processing/combination.py
image_processing/processing/transformation.py
image_processing/utils/__init__.py
image_processing/utils/io.py
image_processing/utils/plot.py
image_processing_mathpr-0.1.0.dist-info/licenses/LICENSE
image_processing_mathpr-0.1.0.dist-info/METADATA
image_processing_mathpr-0.1.0.dist-info/WHEEL
image_processing_mathpr-0.1.0.dist-info/top_level.txt
image_processing_mathpr-0.1.0.dist-info/RECORD
