Metadata-Version: 2.4
Name: image-processing-mathpr
Version: 0.1.0
Summary: Tools for histogram matching, structural similarity, resizing, reading, saving, and plotting images.
Home-page: https://github.com/MatheusPRodrigues/image-processing-package
Author: Matheus
Author-email: Matheus <matherodrigues17@gmail.com>
License: MIT License
Project-URL: Homepage, https://github.com/MatheusPRodrigues/image-processing-package
Project-URL: Bug Tracker, https://github.com/MatheusPRodrigues/image-processing-package/issues
Requires-Python: >=3.5
License-File: LICENSE
Requires-Dist: matplotlib
Requires-Dist: numpy
Requires-Dist: scikit-image>=0.16.1
Dynamic: author
Dynamic: home-page
Dynamic: license-file
Dynamic: requires-python
